<?xml version="1.0" encoding="UTF-8"?>
<!DOCTYPE plist PUBLIC "-//Apple//DTD PLIST 1.0//EN" "http://www.apple.com/DTDs/PropertyList-1.0.dtd">
<plist version="1.0">
<dict>
	<key>DTPlatformBuild</key>
	<string>11B508</string>
	<key>CFBundleName</key>
	<string>CookingDashFree</string>
	<key>DTXcode</key>
	<string>0502</string>
	<key>DTSDKName</key>
	<string>iphoneos7.0</string>
	<key>UISupportedInterfaceOrientations</key>
	<array>
		<string>UIInterfaceOrientationLandscapeRight</string>
		<string>UIInterfaceOrientationLandscapeLeft</string>
	</array>
	<key>CFBundleDisplayName</key>
	<string>Cook DASH</string>
	<key>DTSDKBuild</key>
	<string>11B508</string>
	<key>CFBundleDevelopmentRegion</key>
	<string>en</string>
	<key>CFBundleVersion</key>
	<string>2.25.3</string>
	<key>BuildMachineOSBuild</key>
	<string>12F45</string>
	<key>UIStatusBarHidden</key>
	<true/>
	<key>CFBundlePackageType</key>
	<string>APPL</string>
	<key>DTPlatformName</key>
	<string>iphoneos</string>
	<key>CFBundleSupportedPlatforms</key>
	<array>
		<string>iPhoneOS</string>
	</array>
	<key>FacebookAppID</key>
	<string>367720116666303</string>
	<key>CFBundleInfoDictionaryVersion</key>
	<string>6.0</string>
	<key>CFBundleExecutable</key>
	<string>CookingDashFree</string>
	<key>DTCompiler</key>
	<string>com.apple.compilers.llvm.clang.1_0</string>
	<key>UIViewControllerBasedStatusBarAppearance</key>
	<false/>
	<key>MinimumOSVersion</key>
	<string>4.3</string>
	<key>CFBundleResourceSpecification</key>
	<string>ResourceRules.plist</string>
	<key>CFBundleSignature</key>
	<string>????</string>
	<key>UIDeviceFamily</key>
	<array>
		<integer>1</integer>
		<integer>2</integer>
	</array>
	<key>CFBundleURLTypes</key>
	<array>
		<dict>
			<key>CFBundleTypeRole</key>
			<string>Editor</string>
			<key>CFBundleURLName</key>
			<string>com.playfirst.cookingdashlite</string>
			<key>CFBundleURLSchemes</key>
			<array>
				<string>com.playfirst.cookingdashlite</string>
				<string>fb367720116666303</string>
			</array>
		</dict>
	</array>
	<key>UIInterfaceOrientation</key>
	<string>UIInterfaceOrientationLandscapeRight</string>
	<key>CFBundleLocalizations</key>
	<array>
		<string>en</string>
		<string>de</string>
		<string>es</string>
		<string>fr</string>
		<string>it</string>
	</array>
	<key>DTXcodeBuild</key>
	<string>5A3005</string>
	<key>CFBundleIdentifier</key>
	<string>com.playfirst.cookingdashlite</string>
	<key>UIPrerenderedIcon</key>
	<true/>
	<key>DTPlatformVersion</key>
	<string>7.0</string>
	<key>CFBundleIconFiles</key>
	<array>
		<string>Icon-OS6-iPad</string>
		<string>Icon-OS6-iPadR</string>
		<string>Icon-OS6-iPhone</string>
		<string>Icon-OS6-iPhoneR</string>
		<string>Icon-OS7-iPad</string>
		<string>Icon-OS7-iPadR</string>
		<string>Icon-OS7-iPhoneR</string>
	</array>
	<key>LSRequiresIPhoneOS</key>
	<true/>
</dict>
</plist>
