<?xml version="1.0" encoding="UTF-8"?>
<!DOCTYPE plist PUBLIC "-//Apple//DTD PLIST 1.0//EN" "http://www.apple.com/DTDs/PropertyList-1.0.dtd">
<plist version="1.0">
<dict>
	<key>DTCompiler</key>
	<string>com.apple.compilers.llvm.clang.1_0</string>
	<key>CFBundleInfoDictionaryVersion</key>
	<string>6.0</string>
	<key>UIViewGroupOpacity</key>
	<true/>
	<key>DTPlatformVersion</key>
	<string>8.1</string>
	<key>CFBundleName</key>
	<string>Register</string>
	<key>DTSDKName</key>
	<string>iphoneos8.1</string>
	<key>CFBundleIcons</key>
	<dict>
		<key>CFBundlePrimaryIcon</key>
		<dict>
			<key>CFBundleIconFiles</key>
			<array>
				<string>AppStoreIcon29x29</string>
				<string>AppStoreIcon40x40</string>
				<string>AppStoreIcon57x57</string>
				<string>AppStoreIcon60x60</string>
			</array>
			<key>UIPrerenderedIcon</key>
			<true/>
		</dict>
	</dict>
	<key>UIStatusBarStyle</key>
	<string>UIStatusBarStyleDefault</string>
	<key>LSRequiresIPhoneOS</key>
	<true/>
	<key>CFBundleDisplayName</key>
	<string>Register</string>
	<key>NSLocationWhenInUseUsageDescription</key>
	<string>To protect buyers and sellers, Square requires location information for every payment.</string>
	<key>UIBackgroundModes</key>
	<array>
		<string>fetch</string>
		<string>external-accessory</string>
	</array>
	<key>UISupportedExternalAccessoryProtocols</key>
	<array>
		<string>com.squareup.s015</string>
		<string>com.squareup.s020</string>
		<string>com.squareup.s025</string>
		<string>com.socketmobile.chs</string>
		<string>jp.star-m.starpro</string>
	</array>
	<key>NSCameraUsageDescription</key>
	<string>Upload your account logo, feature photo, and product images with the photos stored on your mobile device.</string>
	<key>CFBundleShortVersionString</key>
	<string>4.16</string>
	<key>NSLocationAlwaysUsageDescription</key>
	<string>To protect buyers and sellers, Square requires location information for every payment.</string>
	<key>UISupportedInterfaceOrientations</key>
	<array>
		<string>UIInterfaceOrientationPortrait</string>
		<string>UIInterfaceOrientationPortraitUpsideDown</string>
		<string>UIInterfaceOrientationLandscapeLeft</string>
		<string>UIInterfaceOrientationLandscapeRight</string>
	</array>
	<key>DTSDKBuild</key>
	<string>12B411</string>
	<key>BuildMachineOSBuild</key>
	<string>14B25</string>
	<key>DTPlatformBuild</key>
	<string>12B411</string>
	<key>CFBundlePackageType</key>
	<string>APPL</string>
	<key>DTXcodeBuild</key>
	<string>6A2008a</string>
	<key>CFBundleDevelopmentRegion</key>
	<string>English</string>
	<key>UIAppFonts</key>
	<array>
		<string>SQMarket-Medium.otf</string>
		<string>SQMarket-Regular.otf</string>
	</array>
	<key>CFBundleVersion</key>
	<string>4160001</string>
	<key>CFBundleSupportedPlatforms</key>
	<array>
		<string>iPhoneOS</string>
	</array>
	<key>MinimumOSVersion</key>
	<string>7.0</string>
	<key>UIDeviceFamily</key>
	<array>
		<integer>1</integer>
		<integer>2</integer>
	</array>
	<key>NSMicrophoneUsageDescription</key>
	<string>Square Reader uses the microphone connection in your headphone jack to send payment card data to your device.</string>
	<key>CFBundleIdentifier</key>
	<string>com.squareup.square</string>
	<key>DTXcode</key>
	<string>0611</string>
	<key>NSLocationUsageDescription</key>
	<string>To protect buyers and sellers, Square requires location information for every payment.</string>
	<key>CFBundleExecutable</key>
	<string>Square</string>
	<key>NSMainNibFile~ipad</key>
	<string></string>
	<key>CFBundleIcons~ipad</key>
	<dict>
		<key>CFBundlePrimaryIcon</key>
		<dict>
			<key>CFBundleIconFiles</key>
			<array>
				<string>AppStoreIcon29x29</string>
				<string>AppStoreIcon40x40</string>
				<string>AppStoreIcon57x57</string>
				<string>AppStoreIcon60x60</string>
				<string>AppStoreIcon50x50</string>
				<string>AppStoreIcon72x72</string>
				<string>AppStoreIcon76x76</string>
			</array>
			<key>UIPrerenderedIcon</key>
			<true/>
		</dict>
	</dict>
	<key>CFBundleSignature</key>
	<string>????</string>
	<key>DTPlatformName</key>
	<string>iphoneos</string>
	<key>CFBundleURLTypes</key>
	<array>
		<dict>
			<key>CFBundleURLName</key>
			<string>Square Register Internal API (Alpha)</string>
			<key>CFBundleURLSchemes</key>
			<array>
				<string>square-register-internal-alpha</string>
			</array>
		</dict>
		<dict>
			<key>CFBundleURLName</key>
			<string>Square Register URL</string>
			<key>CFBundleURLSchemes</key>
			<array>
				<string>square-register</string>
			</array>
		</dict>
		<dict>
			<key>CFBundleURLName</key>
			<string>Square Register Terminal URL</string>
			<key>CFBundleURLSchemes</key>
			<array>
				<string>square-register-terminal</string>
			</array>
		</dict>
		<dict>
			<key>CFBundleTypeRole</key>
			<string>Editor</string>
			<key>CFBundleURLName</key>
			<string>Square Commerce API URL</string>
			<key>CFBundleURLSchemes</key>
			<array>
				<string>square-commerce-v1</string>
			</array>
		</dict>
	</array>
</dict>
</plist>
