<?xml version="1.0" encoding="UTF-8"?>
<!DOCTYPE plist PUBLIC "-//Apple//DTD PLIST 1.0//EN" "http://www.apple.com/DTDs/PropertyList-1.0.dtd">
<plist version="1.0">
<dict>
	<key>DTCompiler</key>
	<string>com.apple.compilers.llvm.clang.1_0</string>
	<key>CFBundleInfoDictionaryVersion</key>
	<string>6.0</string>
	<key>UISupportedInterfaceOrientations~ipad</key>
	<array>
		<string>UIInterfaceOrientationLandscapeLeft</string>
		<string>UIInterfaceOrientationLandscapeRight</string>
		<string>UIInterfaceOrientationPortrait</string>
		<string>UIInterfaceOrientationPortraitUpsideDown</string>
	</array>
	<key>DTPlatformVersion</key>
	<string>8.2</string>
	<key>CFBundleName</key>
	<string>ITK</string>
	<key>DTSDKName</key>
	<string>iphoneos8.2</string>
	<key>BRVersion</key>
	<string>4.7.32</string>
	<key>CFBundleIconFiles~ipad</key>
	<array>
		<string>Icon58x58</string>
		<string>Icon29x29</string>
		<string>Icon80x80</string>
		<string>Icon40x40</string>
		<string>Icon152x152</string>
		<string>Icon76x76</string>
		<string>Icon144x144</string>
		<string>Icon72x72</string>
		<string>Icon120x120</string>
		<string>Icon114x114</string>
		<string>Icon57x57</string>
	</array>
	<key>UIViewControllerBasedStatusBarAppearance</key>
	<false/>
	<key>UIStatusBarStyle</key>
	<string>UIStatusBarStyleBlackOpaque</string>
	<key>LSRequiresIPhoneOS</key>
	<true/>
	<key>CFBundleDisplayName</key>
	<string>In the Kitchen</string>
	<key>Version</key>
	<string>4.7</string>
	<key>DTSDKBuild</key>
	<string>12D508</string>
	<key>CFBundleShortVersionString</key>
	<string>4.7</string>
	<key>UISupportedInterfaceOrientations</key>
	<array>
		<string>UIInterfaceOrientationPortrait</string>
		<string>UIInterfaceOrientationLandscapeLeft</string>
		<string>UIInterfaceOrientationLandscapeRight</string>
	</array>
	<key>CFBundleSupportedPlatforms</key>
	<array>
		<string>iPhoneOS</string>
	</array>
	<key>BuildMachineOSBuild</key>
	<string>14C1510</string>
	<key>DTPlatformBuild</key>
	<string>12D508</string>
	<key>CFBundlePackageType</key>
	<string>APPL</string>
	<key>DTXcodeBuild</key>
	<string>6C131e</string>
	<key>CFBundleDevelopmentRegion</key>
	<string>en</string>
	<key>UIAppFonts</key>
	<array>
		<string>ss-standard.otf</string>
		<string>ITCFranklinGothicStd-BkCp.otf</string>
	</array>
	<key>CFBundleVersion</key>
	<string>32</string>
	<key>UIPrerenderedIcon</key>
	<true/>
	<key>UIStatusBarHidden</key>
	<true/>
	<key>MinimumOSVersion</key>
	<string>7.0</string>
	<key>UIDeviceFamily</key>
	<array>
		<integer>1</integer>
		<integer>2</integer>
	</array>
	<key>CFBundleIdentifier</key>
	<string>com.sni.iphone.applications.ITKApp</string>
	<key>CFBundleIconFiles</key>
	<array>
		<string>Icon50x50</string>
		<string>Icon100x100</string>
		<string>Icon80x80</string>
		<string>Icon58x58</string>
		<string>Icon29x29</string>
		<string>Icon120x120</string>
		<string>Icon114x114</string>
		<string>Icon72x72</string>
		<string>Icon57x57</string>
		<string>Icon144x144</string>
	</array>
	<key>DTXcode</key>
	<string>0620</string>
	<key>UILaunchImages~ipad</key>
	<array>
		<dict>
			<key>UILaunchImageOrientation</key>
			<string>Landscape</string>
			<key>UILaunchImageName</key>
			<string>Default-Landscape</string>
			<key>UILaunchImageSize</key>
			<string>{768, 1024}</string>
			<key>UILaunchImageMinimumOSVersion</key>
			<string>7.0</string>
		</dict>
		<dict>
			<key>UILaunchImageOrientation</key>
			<string>Portrait</string>
			<key>UILaunchImageName</key>
			<string>Default-Portrait</string>
			<key>UILaunchImageSize</key>
			<string>{768, 1024}</string>
			<key>UILaunchImageMinimumOSVersion</key>
			<string>7.0</string>
		</dict>
	</array>
	<key>CFBundleExecutable</key>
	<string>ITK</string>
	<key>CFBundleSignature</key>
	<string>????</string>
	<key>DTPlatformName</key>
	<string>iphoneos</string>
	<key>CFBundleURLTypes</key>
	<array>
		<dict>
			<key>CFBundleTypeRole</key>
			<string>Editor</string>
			<key>CFBundleURLName</key>
			<string>com.sni.iphone.applications.ITKApp</string>
			<key>CFBundleURLSchemes</key>
			<array>
				<string>com.sni.iphone.applications.ITKApp</string>
			</array>
		</dict>
	</array>
</dict>
</plist>
