<?xml version="1.0" encoding="UTF-8"?>
<!DOCTYPE plist PUBLIC "-//Apple//DTD PLIST 1.0//EN" "http://www.apple.com/DTDs/PropertyList-1.0.dtd">
<plist version="1.0">
<dict>
	<key>UIRequiredDeviceCapabilities</key>
	<array>
		<string>armv7</string>
	</array>
	<key>DTCompiler</key>
	<string>com.apple.compilers.llvm.clang.1_0</string>
	<key>CFBundleInfoDictionaryVersion</key>
	<string>6.0</string>
	<key>UISupportedInterfaceOrientations~ipad</key>
	<array>
		<string>UIInterfaceOrientationPortrait</string>
		<string>UIInterfaceOrientationPortraitUpsideDown</string>
		<string>UIInterfaceOrientationLandscapeLeft</string>
		<string>UIInterfaceOrientationLandscapeRight</string>
	</array>
	<key>DTPlatformVersion</key>
	<string>8.3</string>
	<key>CFBundleName</key>
	<string>WABC</string>
	<key>DTSDKName</key>
	<string>iphoneos8.3</string>
	<key>UIViewControllerBasedStatusBarAppearance</key>
	<false/>
	<key>UIMainStoryboardFile~ipad</key>
	<string>MainStoryboard</string>
	<key>CFBundleIcons</key>
	<dict>
		<key>CFBundlePrimaryIcon</key>
		<dict>
			<key>CFBundleIconFiles</key>
			<array>
				<string>WABC-AppIcon29x29</string>
				<string>WABC-AppIcon40x40</string>
				<string>WABC-AppIcon60x60</string>
			</array>
		</dict>
	</dict>
	<key>UIStatusBarStyle</key>
	<string>UIStatusBarStyleBlackOpaque</string>
	<key>LSRequiresIPhoneOS</key>
	<true/>
	<key>CFBundleDisplayName</key>
	<string>ABC7NY</string>
	<key>NSLocationWhenInUseUsageDescription</key>
	<string>To provide local news and weather</string>
	<key>UIMainStoryboardFile~iphone</key>
	<string>MainStoryboard-iPhone</string>
	<key>DTSDKBuild</key>
	<string>12F69</string>
	<key>CFBundleShortVersionString</key>
	<string>4.1.0</string>
	<key>UISupportedInterfaceOrientations</key>
	<array>
		<string>UIInterfaceOrientationPortrait</string>
		<string>UIInterfaceOrientationPortraitUpsideDown</string>
		<string>UIInterfaceOrientationLandscapeLeft</string>
		<string>UIInterfaceOrientationLandscapeRight</string>
	</array>
	<key>CFBundleSupportedPlatforms</key>
	<array>
		<string>iPhoneOS</string>
	</array>
	<key>BuildMachineOSBuild</key>
	<string>14C1510</string>
	<key>DTPlatformBuild</key>
	<string>12F69</string>
	<key>CFBundlePackageType</key>
	<string>APPL</string>
	<key>DTXcodeBuild</key>
	<string>6D570</string>
	<key>CFBundleDevelopmentRegion</key>
	<string>en</string>
	<key>testFlightAppToken</key>
	<string>50059e54-fe44-4e7a-93a3-a565dc0f6838</string>
	<key>CFBundleVersion</key>
	<string>4.1.002</string>
	<key>UIAppFonts</key>
	<array>
		<string>Gotham-Bold.otf</string>
		<string>Gotham-Black.otf</string>
		<string>Gotham-Book.otf</string>
		<string>Gotham-Light.otf</string>
		<string>Gotham-Medium.otf</string>
		<string>Gotham-Medium-Condensed.otf</string>
		<string>GothamXNarrow-Bold.otf</string>
		<string>GothamXNarrow-Medium.otf</string>
	</array>
	<key>UIPrerenderedIcon</key>
	<true/>
	<key>MinimumOSVersion</key>
	<string>8.0</string>
	<key>UIDeviceFamily</key>
	<array>
		<integer>1</integer>
		<integer>2</integer>
	</array>
	<key>CFBundleIdentifier</key>
	<string>com.go.abclocal.wabcapp</string>
	<key>DTXcode</key>
	<string>0630</string>
	<key>NSLocationUsageDescription</key>
	<string>To provide local news and weather</string>
	<key>CFBundleExecutable</key>
	<string>WABC</string>
	<key>CFBundleIcons~ipad</key>
	<dict>
		<key>CFBundlePrimaryIcon</key>
		<dict>
			<key>CFBundleIconFiles</key>
			<array>
				<string>WABC-AppIcon29x29</string>
				<string>WABC-AppIcon40x40</string>
				<string>WABC-AppIcon60x60</string>
				<string>WABC-AppIcon76x76</string>
			</array>
		</dict>
	</dict>
	<key>UIMainStoryboardFile</key>
	<string>MainStoryboard-iPhone</string>
	<key>CFBundleSignature</key>
	<string>????</string>
	<key>DTPlatformName</key>
	<string>iphoneos</string>
	<key>CFBundleURLTypes</key>
	<array>
		<dict>
			<key>CFBundleTypeRole</key>
			<string>None</string>
			<key>CFBundleURLName</key>
			<string>com.go.abclocal.wabcapp.launch</string>
			<key>CFBundleURLSchemes</key>
			<array>
				<string>ABC-WABC</string>
			</array>
		</dict>
	</array>
</dict>
</plist>
