<?xml version="1.0" encoding="UTF-8"?>
<!DOCTYPE plist PUBLIC "-//Apple//DTD PLIST 1.0//EN" "http://www.apple.com/DTDs/PropertyList-1.0.dtd">
<plist version="1.0">
<dict>
	<key>CFBundlePackageType</key>
	<string>APPL</string>
	<key>terms_fr_url</key>
	<string>http://fr.info.sympatico.ca/go/conditions-utilisation</string>
	<key>DTPlatformVersion</key>
	<string>5.1</string>
	<key>DTSDKBuild</key>
	<string>8H7</string>
	<key>feat_en_url</key>
	<string>http://bsympatico.vo.llnwd.net/o35/feeds/mobile/Featured_Articles/Featured_Articles.xml</string>
	<key>top_fr_url</key>
	<string>http://content-resources.sympatico.ca/content/feeds/mobile/HP_TopStories_fr.xml</string>
	<key>pushPortNumber</key>
	<string>443</string>
	<key>LSRequiresIPhoneOS</key>
	<true/>
	<key>NSMainNibFile</key>
	<string>MainWindow</string>
	<key>flurry_key</key>
	<string>67677MTEVLHN28QCT9Y3</string>
	<key>CFBundleDisplayName</key>
	<string>Sympatico.ca</string>
	<key>CFBundleDocumentTypes</key>
	<array>
	</array>
	<key>DTXcodeBuild</key>
	<string>4E1019</string>
	<key>UTExportedTypeDeclarations</key>
	<array>
	</array>
	<key>CFBundleIdentifier</key>
	<string>com.fivemobile.sympaticonews</string>
	<key>weatherURL_FR</key>
	<string>http://m.sympatico.ca/fr/weather</string>
	<key>UIDeviceFamily</key>
	<array>
		<integer>1</integer>
	</array>
	<key>CFBundleSignature</key>
	<string>????</string>
	<key>CFBundleInfoDictionaryVersion</key>
	<string>6.0</string>
	<key>CFBundleResourceSpecification</key>
	<string>ResourceRules.plist</string>
	<key>CFBundleSupportedPlatforms</key>
	<array>
		<string>iPhoneOS</string>
	</array>
	<key>links_Unspecified</key>
	<string>http://bsympatico.vo.llnwd.net/o35/feeds/mobile/global/portfolio.xml</string>
	<key>pushID</key>
	<string>SYMPATICO_PROD</string>
	<key>privacy_fr_url</key>
	<string>http://fr.info.sympatico.ca/go/confidentialite</string>
	<key>MinimumOSVersion</key>
	<string>4.0</string>
	<key>CFBundleIconFiles</key>
	<array>
		<string>Icon.png</string>
		<string>Icon@2x.png</string>
	</array>
	<key>CFBundleName</key>
	<string>Sympatico</string>
	<key>CFBundleShortVersionString</key>
	<string>1.0.3</string>
	<key>UIStatusBarHidden</key>
	<true/>
	<key>privacy_en_url</key>
	<string>http://en.info.sympatico.ca/go/privacy</string>
	<key>UIApplicationExitsOnSuspend</key>
	<false/>
	<key>CFBundleExecutable</key>
	<string>Sympatico</string>
	<key>UTImportedTypeDeclarations</key>
	<array>
	</array>
	<key>links_Female</key>
	<string>http://bsympatico.vo.llnwd.net/o35/feeds/mobile/global/portfolio_f.xml</string>
	<key>UIPrerenderedIcon</key>
	<true/>
	<key>UIRequiresPersistentWiFi</key>
	<true/>
	<key>BuildMachineOSBuild</key>
	<string>11D50</string>
	<key>links_Male</key>
	<string>http://bsympatico.vo.llnwd.net/o35/feeds/mobile/global/portfolio_m.xml</string>
	<key>DTPlatformName</key>
	<string>iphoneos</string>
	<key>pushHostName</key>
	<string>push.fivemobile.com</string>
	<key>weatherURL_EN</key>
	<string>http://m.sympatico.ca/en/weather</string>
	<key>terms_en_url</key>
	<string>http://en.info.sympatico.ca/go/tou</string>
	<key>DTCompiler</key>
	<string>com.apple.compilers.llvmgcc42</string>
	<key>CFBundleDevelopmentRegion</key>
	<string>English</string>
	<key>CFBundleVersion</key>
	<string>1.0.3</string>
	<key>CFBundleURLTypes</key>
	<array>
		<dict>
			<key>CFBundleURLSchemes</key>
			<array>
				<string>fb153750811350306</string>
			</array>
		</dict>
	</array>
	<key>DTSDKName</key>
	<string>iphoneos4.3</string>
	<key>top_en_url</key>
	<string>http://content-resources.sympatico.ca/content/feeds/mobile/HP_TopStories.xml</string>
	<key>flurry_key_note</key>
	<string>place the dev or production flurry key into flurry_key when building the associated build</string>
	<key>DTPlatformBuild</key>
	<string>9B176</string>
	<key>DTXcode</key>
	<string>0431</string>
	<key>feat_fr_url</key>
	<string>http://bsympatico.vo.llnwd.net/o35/feeds/mobile/Featured_Articles_FR/Featured_Articles_FR.xml</string>
</dict>
</plist>
