<?xml version="1.0" encoding="UTF-8"?>
<!DOCTYPE plist PUBLIC "-//Apple//DTD PLIST 1.0//EN" "http://www.apple.com/DTDs/PropertyList-1.0.dtd">
<plist version="1.0">
<dict>
	<key>DTCompiler</key>
	<string>com.apple.compilers.llvm.clang.1_0</string>
	<key>CFBundleInfoDictionaryVersion</key>
	<string>6.0</string>
	<key>UISupportedInterfaceOrientations~ipad</key>
	<array>
		<string>UIInterfaceOrientationPortrait</string>
		<string>UIInterfaceOrientationPortraitUpsideDown</string>
		<string>UIInterfaceOrientationLandscapeLeft</string>
		<string>UIInterfaceOrientationLandscapeRight</string>
	</array>
	<key>DTPlatformVersion</key>
	<string>7.1</string>
	<key>CFBundleIconFile</key>
	<string>beautylish_app_icon~iphone.png</string>
	<key>CFBundleName</key>
	<string>Beautylish</string>
	<key>DTSDKName</key>
	<string>iphoneos7.1</string>
	<key>UIViewControllerBasedStatusBarAppearance</key>
	<string>YES</string>
	<key>CFBundleIcons</key>
	<dict>
		<key>CFBundlePrimaryIcon</key>
		<dict>
			<key>CFBundleIconFiles</key>
			<array>
				<string>beautylish_app_icon_spotlight_ios7</string>
				<string>beautylish_app_icon_spotlight</string>
				<string>beautylish_app_icon_ios7</string>
				<string>beautylish_app_icon.png</string>
				<string>beautylish_app_icon~iphone.png</string>
				<string>beautylish_app_icon~iphone@2x.png</string>
				<string>beautylish_app_icon@2x.png</string>
			</array>
			<key>UIPrerenderedIcon</key>
			<true/>
		</dict>
	</dict>
	<key>UIStatusBarStyle</key>
	<string>UIStatusBarStyleBlackOpaque</string>
	<key>LSRequiresIPhoneOS</key>
	<true/>
	<key>CFBundleDisplayName</key>
	<string>Beautylish</string>
	<key>UIStatusBarHidden~ipad</key>
	<false/>
	<key>DTSDKBuild</key>
	<string>11D167</string>
	<key>CFBundleShortVersionString</key>
	<string>2.20</string>
	<key>CFBundleSupportedPlatforms</key>
	<array>
		<string>iPhoneOS</string>
	</array>
	<key>UISupportedInterfaceOrientations</key>
	<array>
		<string>UIInterfaceOrientationPortrait</string>
		<string>UIInterfaceOrientationPortraitUpsideDown</string>
		<string>UIInterfaceOrientationLandscapeLeft</string>
		<string>UIInterfaceOrientationLandscapeRight</string>
	</array>
	<key>BuildMachineOSBuild</key>
	<string>13C1021</string>
	<key>DTPlatformBuild</key>
	<string>11D167</string>
	<key>CFBundlePackageType</key>
	<string>APPL</string>
	<key>DTXcodeBuild</key>
	<string>5B1008</string>
	<key>CFBundleDevelopmentRegion</key>
	<string>en</string>
	<key>UIAppFonts</key>
	<array>
		<string>lettergothicmedium.ttf</string>
		<string>av_heavy.ttf</string>
		<string>av_light.ttf</string>
	</array>
	<key>CFBundleVersion</key>
	<string>2.20</string>
	<key>UIPrerenderedIcon</key>
	<true/>
	<key>MinimumOSVersion</key>
	<string>6.0</string>
	<key>UIDeviceFamily</key>
	<array>
		<integer>1</integer>
		<integer>2</integer>
	</array>
	<key>NSMainNibFile</key>
	<string>MainWindow_iphone</string>
	<key>CFBundleIdentifier</key>
	<string>com.beautylish.Beautylish</string>
	<key>CFBundleIconFiles</key>
	<array>
		<string>beautylish_app_icon.png</string>
		<string>beautylish_app_icon~iphone.png</string>
		<string>beautylish_app_icon~iphone@2x.png</string>
		<string>beautylish_app_icon@2x.png</string>
	</array>
	<key>DTXcode</key>
	<string>0511</string>
	<key>UILaunchImages~ipad</key>
	<array>
		<dict>
			<key>UILaunchImageOrientation</key>
			<string>Portrait</string>
			<key>UILaunchImageName</key>
			<string>Default-Portrait-ios7</string>
			<key>UILaunchImageSize</key>
			<string>{768, 1024}</string>
			<key>UILaunchImageMinimumOSVersion</key>
			<string>7.0</string>
		</dict>
		<dict>
			<key>UILaunchImageOrientation</key>
			<string>Landscape</string>
			<key>UILaunchImageName</key>
			<string>Default-Landscape-ios7</string>
			<key>UILaunchImageSize</key>
			<string>{768, 1024}</string>
			<key>UILaunchImageMinimumOSVersion</key>
			<string>7.0</string>
		</dict>
		<dict>
			<key>UILaunchImageOrientation</key>
			<string>Portrait</string>
			<key>UILaunchImageName</key>
			<string>Default-Landscape-ios7</string>
			<key>UILaunchImageSize</key>
			<string>{768, 1024}</string>
			<key>UILaunchImageMinimumOSVersion</key>
			<string>7.0</string>
		</dict>
	</array>
	<key>CFBundleExecutable</key>
	<string>Beautylish</string>
	<key>NSMainNibFile~ipad</key>
	<string>MainWindow_ipad</string>
	<key>CFBundleIcons~ipad</key>
	<dict>
		<key>CFBundlePrimaryIcon</key>
		<dict>
			<key>CFBundleIconFiles</key>
			<array>
				<string>beautylish_app_icon_40</string>
				<string>beautylish_app_icon_50</string>
				<string>beautylish_app_icon_ios7_ipad</string>
				<string>beautylish_app_icon_spotlight_ios7</string>
				<string>beautylish_app_icon_spotlight</string>
				<string>beautylish_app_icon_ios7</string>
				<string>beautylish_app_icon.png</string>
				<string>beautylish_app_icon~iphone.png</string>
				<string>beautylish_app_icon~iphone@2x.png</string>
				<string>beautylish_app_icon@2x.png</string>
			</array>
			<key>UIPrerenderedIcon</key>
			<true/>
		</dict>
	</dict>
	<key>CFBundleSignature</key>
	<string>????</string>
	<key>DTPlatformName</key>
	<string>iphoneos</string>
	<key>CFBundleResourceSpecification</key>
	<string>ResourceRules.plist</string>
	<key>CFBundleURLTypes</key>
	<array>
		<dict>
			<key>CFBundleTypeRole</key>
			<string>Editor</string>
			<key>CFBundleURLName</key>
			<string>com.beautylish.Beautylish</string>
			<key>CFBundleURLSchemes</key>
			<array>
				<string>beautylish</string>
				<string>com.beautylish.Beautylish</string>
				<string>fb251090226745</string>
				<string>fb113392765349220</string>
			</array>
		</dict>
	</array>
</dict>
</plist>
