<?xml version="1.0" encoding="UTF-8"?>
<!DOCTYPE plist PUBLIC "-//Apple//DTD PLIST 1.0//EN" "http://www.apple.com/DTDs/PropertyList-1.0.dtd">
<plist version="1.0">
<dict>
	<key>DTPlatformBuild</key>
	<string>11D167</string>
	<key>CFBundleAllowMixedLocalizations</key>
	<true/>
	<key>CFBundleName</key>
	<string>SinaVDun</string>
	<key>DTXcode</key>
	<string>0511</string>
	<key>DTSDKName</key>
	<string>iphoneos7.1</string>
	<key>DTSDKBuild</key>
	<string>11D167</string>
	<key>CFBundleDevelopmentRegion</key>
	<string>zh_CN</string>
	<key>CFBundleVersion</key>
	<string>1.7.9</string>
	<key>BuildMachineOSBuild</key>
	<string>13F34</string>
	<key>UIStatusBarHidden</key>
	<false/>
	<key>CFBundleShortVersionString</key>
	<string>1.7.9</string>
	<key>CFBundlePackageType</key>
	<string>APPL</string>
	<key>CFBundleSupportedPlatforms</key>
	<array>
		<string>iPhoneOS</string>
	</array>
	<key>DTPlatformName</key>
	<string>iphoneos</string>
	<key>CFBundleInfoDictionaryVersion</key>
	<string>6.0</string>
	<key>UIRequiredDeviceCapabilities</key>
	<array>
		<string>armv7</string>
	</array>
	<key>CFBundleExecutable</key>
	<string>SinaToken</string>
	<key>DTCompiler</key>
	<string>com.apple.compilers.llvm.clang.1_0</string>
	<key>MinimumOSVersion</key>
	<string>6.0</string>
	<key>UIDeviceFamily</key>
	<array>
		<integer>1</integer>
	</array>
	<key>CFBundleURLTypes</key>
	<array>
		<dict>
			<key>CFBundleTypeRole</key>
			<string>Editor</string>
			<key>CFBundleURLName</key>
			<string>com.sina.vdun</string>
			<key>CFBundleURLSchemes</key>
			<array>
				<string>sinavdun</string>
			</array>
		</dict>
		<dict>
			<key>CFBundleTypeRole</key>
			<string>Editor</string>
			<key>CFBundleURLName</key>
			<string>com.sina.vdun</string>
			<key>CFBundleURLSchemes</key>
			<array>
				<string>sinaweibosso.2317377944</string>
			</array>
		</dict>
	</array>
	<key>DTXcodeBuild</key>
	<string>5B1008</string>
	<key>CFBundleIdentifier</key>
	<string>com.sina.sinaVirtualWall</string>
	<key>UIAppFonts</key>
	<array>
		<string>digifaw_0.ttf</string>
	</array>
	<key>DTPlatformVersion</key>
	<string>7.1</string>
	<key>CFBundleIconFiles</key>
	<array>
		<string>icon</string>
		<string>icon-29</string>
		<string>icon-80</string>
		<string>icon-58</string>
		<string>icon-120</string>
		<string>icon.png</string>
		<string>icon@2x.png</string>
	</array>
	<key>LSRequiresIPhoneOS</key>
	<true/>
	<key>CFBundleDisplayName</key>
	<string>新浪微盾</string>
	<key>UIPrerenderedIcon</key>
	<true/>
	<key>CFBundleSignature</key>
	<string>????</string>
	<key>UISupportedInterfaceOrientations</key>
	<array>
		<string>UIInterfaceOrientationPortrait</string>
	</array>
	<key>CFBundleResourceSpecification</key>
	<string>ResourceRules.plist</string>
</dict>
</plist>
