<?xml version="1.0" encoding="UTF-8"?>
<!DOCTYPE plist PUBLIC "-//Apple//DTD PLIST 1.0//EN" "http://www.apple.com/DTDs/PropertyList-1.0.dtd">
<plist version="1.0">
<dict>
	<key>DTCompiler</key>
	<string>com.apple.compilers.llvm.clang.1_0</string>
	<key>CFBundleInfoDictionaryVersion</key>
	<string>6.0</string>
	<key>UISupportedInterfaceOrientations~ipad</key>
	<array>
		<string>UIInterfaceOrientationLandscapeLeft</string>
		<string>UIInterfaceOrientationLandscapeRight</string>
	</array>
	<key>DTPlatformVersion</key>
	<string>8.1</string>
	<key>CFBundleName</key>
	<string>kaka2h</string>
	<key>DTSDKName</key>
	<string>iphoneos8.1</string>
	<key>UIViewControllerBasedStatusBarAppearance</key>
	<false/>
	<key>CFBundleIcons</key>
	<dict>
		<key>CFBundlePrimaryIcon</key>
		<dict>
			<key>CFBundleIconFiles</key>
			<array>
				<string>Icon-60</string>
				<string>Icon-40</string>
				<string>Icon-Small</string>
				<string>Icon</string>
				<string>icon</string>
			</array>
		</dict>
	</dict>
	<key>UIStatusBarStyle</key>
	<string>UIStatusBarStyleDefault</string>
	<key>UIStatusBarTintParameters</key>
	<dict>
		<key>UINavigationBar</key>
		<dict>
			<key>Style</key>
			<string>UIBarStyleDefault</string>
			<key>TintColor</key>
			<dict>
				<key>Green</key>
				<real>0.374534</real>
				<key>Red</key>
				<real>0.298879</real>
				<key>Blue</key>
				<real>0.505031</real>
			</dict>
			<key>Translucent</key>
			<false/>
		</dict>
	</dict>
	<key>LSRequiresIPhoneOS</key>
	<true/>
	<key>CFBundleDisplayName</key>
	<string>澳門二手市場</string>
	<key>DTSDKBuild</key>
	<string>12B411</string>
	<key>CFBundleShortVersionString</key>
	<string>2.7</string>
	<key>CFBundleSupportedPlatforms</key>
	<array>
		<string>iPhoneOS</string>
	</array>
	<key>UISupportedInterfaceOrientations</key>
	<array>
		<string>UIInterfaceOrientationPortrait</string>
	</array>
	<key>BuildMachineOSBuild</key>
	<string>14A389</string>
	<key>DTPlatformBuild</key>
	<string>12B411</string>
	<key>CFBundlePackageType</key>
	<string>APPL</string>
	<key>DTXcodeBuild</key>
	<string>6A1052d</string>
	<key>CFBundleDevelopmentRegion</key>
	<string>English</string>
	<key>UIPrerenderedIcon</key>
	<true/>
	<key>CFBundleVersion</key>
	<string>2.7.1</string>
	<key>MinimumOSVersion</key>
	<string>6.0</string>
	<key>UIStatusBarHidden</key>
	<true/>
	<key>UIDeviceFamily</key>
	<array>
		<integer>1</integer>
		<integer>2</integer>
	</array>
	<key>CFBundleIdentifier</key>
	<string>com.kakafun.kaka2h</string>
	<key>DTXcode</key>
	<string>0610</string>
	<key>UILaunchImages~ipad</key>
	<array>
		<dict>
			<key>UILaunchImageOrientation</key>
			<string>Landscape</string>
			<key>UILaunchImageName</key>
			<string>Default-Landscape</string>
			<key>UILaunchImageSize</key>
			<string>{768, 1024}</string>
			<key>UILaunchImageMinimumOSVersion</key>
			<string>7.0</string>
		</dict>
		<dict>
			<key>UILaunchImageOrientation</key>
			<string>Portrait</string>
			<key>UILaunchImageName</key>
			<string>Default-Portrait</string>
			<key>UILaunchImageSize</key>
			<string>{768, 1024}</string>
			<key>UILaunchImageMinimumOSVersion</key>
			<string>7.0</string>
		</dict>
	</array>
	<key>CFBundleExecutable</key>
	<string>kaka2h</string>
	<key>NSMainNibFile~ipad</key>
	<string></string>
	<key>CFBundleIcons~ipad</key>
	<dict>
		<key>CFBundlePrimaryIcon</key>
		<dict>
			<key>CFBundleIconFiles</key>
			<array>
				<string>Icon-76</string>
				<string>Icon-Small</string>
				<string>Icon</string>
				<string>Icon-40</string>
				<string>Icon-Small-20</string>
				<string>Icon-Small-50</string>
				<string>icon-72</string>
				<string>icon</string>
			</array>
		</dict>
	</dict>
	<key>CFBundleSignature</key>
	<string>????</string>
	<key>DTPlatformName</key>
	<string>iphoneos</string>
	<key>CFBundleURLTypes</key>
	<array>
		<dict>
			<key>CFBundleTypeRole</key>
			<string>Editor</string>
			<key>CFBundleURLIconFile</key>
			<string>icon-72</string>
			<key>CFBundleURLSchemes</key>
			<array>
				<string>mo2hand</string>
			</array>
			<key>CFBundleURLName</key>
			<string>com.kakafun.kaka2h</string>
		</dict>
	</array>
</dict>
</plist>
