<?xml version="1.0" encoding="UTF-8"?>
<!DOCTYPE plist PUBLIC "-//Apple//DTD PLIST 1.0//EN" "http://www.apple.com/DTDs/PropertyList-1.0.dtd">
<plist version="1.0">
<dict>
	<key>UIRequiredDeviceCapabilities</key>
	<array>
		<string>armv7</string>
	</array>
	<key>CFBundleURLTypes</key>
	<array>
		<dict>
			<key>CFBundleURLSchemes</key>
			<array>
				<string>fb359600970769625</string>
			</array>
		</dict>
		<dict>
			<key>CFBundleTypeRole</key>
			<string>Editor</string>
			<key>CFBundleURLName</key>
			<string>com.hungerstation.ios.hungerstationapp</string>
			<key>CFBundleURLSchemes</key>
			<array>
				<string>hungerstation</string>
			</array>
		</dict>
	</array>
	<key>CFBundleInfoDictionaryVersion</key>
	<string>6.0</string>
	<key>UISupportedInterfaceOrientations~ipad</key>
	<array>
		<string>UIInterfaceOrientationPortrait</string>
	</array>
	<key>DTPlatformVersion</key>
	<string>8.3</string>
	<key>CFBundleName</key>
	<string>hungerstationapp</string>
	<key>DTSDKName</key>
	<string>iphoneos8.3</string>
	<key>CFBundleIcons</key>
	<dict>
		<key>CFBundlePrimaryIcon</key>
		<dict>
			<key>CFBundleIconFiles</key>
			<array>
				<string>AppIcon29x29</string>
				<string>AppIcon40x40</string>
				<string>AppIcon57x57</string>
				<string>AppIcon60x60</string>
				<string>AppIcon120x120</string>
			</array>
		</dict>
	</dict>
	<key>GOOGLE_ANALYTICS_ID</key>
	<string>UA-31949920-4</string>
	<key>LSApplicationCategoryType</key>
	<string></string>
	<key>HUNGERSTATION_APPSECRET</key>
	<string>9a02063422ef562ba96bc49b7eb2459494ac5e3a814947cb4c6a1643f35eecee</string>
	<key>CFBundleDisplayName</key>
	<string>HungerStation</string>
	<key>LSRequiresIPhoneOS</key>
	<true/>
	<key>NSLocationWhenInUseUsageDescription</key>
	<string></string>
	<key>NEWRELIC_TOKEN</key>
	<string>AA8ef06868b0bc5074e1cd9596dfe5958ac42878b6</string>
	<key>DTSDKBuild</key>
	<string>12F69</string>
	<key>CFBundleShortVersionString</key>
	<string>22</string>
	<key>NSLocationAlwaysUsageDescription</key>
	<string></string>
	<key>UISupportedInterfaceOrientations</key>
	<array>
		<string>UIInterfaceOrientationPortrait</string>
	</array>
	<key>CFBundleSupportedPlatforms</key>
	<array>
		<string>iPhoneOS</string>
	</array>
	<key>BuildMachineOSBuild</key>
	<string>14D131</string>
	<key>DTPlatformBuild</key>
	<string>12F69</string>
	<key>CFBundlePackageType</key>
	<string>APPL</string>
	<key>DTXcodeBuild</key>
	<string>6D570</string>
	<key>CFBundleDevelopmentRegion</key>
	<string>en</string>
	<key>TWITTER_CONSUMER_SECRET</key>
	<string>intkL3DMJT6Dl207Wo90eREe5vnij9rjWKKKyQXc</string>
	<key>CFBundleVersion</key>
	<string>28</string>
	<key>UIAppFonts</key>
	<array>
	</array>
	<key>MinimumOSVersion</key>
	<string>7.0</string>
	<key>FacebookAppID</key>
	<string>359600970769625</string>
	<key>UILaunchImages</key>
	<array>
		<dict>
			<key>UILaunchImageOrientation</key>
			<string>Portrait</string>
			<key>UILaunchImageName</key>
			<string>LaunchImage-800-Portrait-736h</string>
			<key>UILaunchImageSize</key>
			<string>{414, 736}</string>
			<key>UILaunchImageMinimumOSVersion</key>
			<string>8.0</string>
		</dict>
		<dict>
			<key>UILaunchImageOrientation</key>
			<string>Portrait</string>
			<key>UILaunchImageName</key>
			<string>LaunchImage-800-667h</string>
			<key>UILaunchImageSize</key>
			<string>{375, 667}</string>
			<key>UILaunchImageMinimumOSVersion</key>
			<string>8.0</string>
		</dict>
		<dict>
			<key>UILaunchImageOrientation</key>
			<string>Portrait</string>
			<key>UILaunchImageName</key>
			<string>LaunchImage-700</string>
			<key>UILaunchImageSize</key>
			<string>{320, 480}</string>
			<key>UILaunchImageMinimumOSVersion</key>
			<string>7.0</string>
		</dict>
		<dict>
			<key>UILaunchImageOrientation</key>
			<string>Portrait</string>
			<key>UILaunchImageName</key>
			<string>LaunchImage-700-568h</string>
			<key>UILaunchImageSize</key>
			<string>{320, 568}</string>
			<key>UILaunchImageMinimumOSVersion</key>
			<string>7.0</string>
		</dict>
		<dict>
			<key>UILaunchImageOrientation</key>
			<string>Portrait</string>
			<key>UILaunchImageName</key>
			<string>LaunchImage-700-Portrait</string>
			<key>UILaunchImageSize</key>
			<string>{768, 1024}</string>
			<key>UILaunchImageMinimumOSVersion</key>
			<string>7.0</string>
		</dict>
	</array>
	<key>UIDeviceFamily</key>
	<array>
		<integer>1</integer>
		<integer>2</integer>
	</array>
	<key>GoogleClientId</key>
	<string>1007442182715-dqrshspgsqpvnsdmuqp9957rd55au7mj.apps.googleusercontent.com</string>
	<key>BASE_URL</key>
	<string>https://hungerstation.com/</string>
	<key>GoogleApiKey</key>
	<string>AIzaSyBprsKMr4OSIfeZ7v_dVa2qRRY0sdec18k</string>
	<key>HUNGERSTATION_APPID</key>
	<string>5f11273c52c332d739f8b111fd518f34daa3fc75d20d82c3ec1c1b99f566e45d</string>
	<key>Fabric</key>
	<dict>
		<key>Kits</key>
		<array>
			<dict>
				<key>KitName</key>
				<string>Crashlytics</string>
				<key>KitInfo</key>
				<dict>
				</dict>
			</dict>
			<dict>
				<key>KitName</key>
				<string>MoPub</string>
				<key>KitInfo</key>
				<dict>
				</dict>
			</dict>
		</array>
		<key>APIKey</key>
		<string>24a01f2f1b1a368dc8d485e85c8ed645e377120d</string>
	</dict>
	<key>CFBundleIdentifier</key>
	<string>com.hungerstation.ios.hungerstationapp</string>
	<key>BASE_API_PATH</key>
	<string>api/v2/</string>
	<key>DTXcode</key>
	<string>0630</string>
	<key>TWITTER_CONSUMER_KEY</key>
	<string>lFB90p9P97MCTLGzPAU4pQ</string>
	<key>CFBundleExecutable</key>
	<string>HungerStation</string>
	<key>CFBundleIcons~ipad</key>
	<dict>
		<key>CFBundlePrimaryIcon</key>
		<dict>
			<key>CFBundleIconFiles</key>
			<array>
				<string>AppIcon29x29</string>
				<string>AppIcon40x40</string>
				<string>AppIcon50x50</string>
				<string>AppIcon72x72</string>
				<string>AppIcon76x76</string>
			</array>
		</dict>
	</dict>
	<key>CFBundleSignature</key>
	<string>????</string>
	<key>DTPlatformName</key>
	<string>iphoneos</string>
	<key>DTCompiler</key>
	<string>com.apple.compilers.llvm.clang.1_0</string>
</dict>
</plist>
