<?xml version="1.0" encoding="UTF-8"?>
<!DOCTYPE plist PUBLIC "-//Apple//DTD PLIST 1.0//EN" "http://www.apple.com/DTDs/PropertyList-1.0.dtd">
<plist version="1.0">
<dict>
	<key>CFBundleURLTypes</key>
	<array>
		<dict>
			<key>CFBundleURLName</key>
			<string>com.stendapps.textcamera</string>
			<key>CFBundleURLSchemes</key>
			<array>
				<string>textcamera</string>
			</array>
		</dict>
	</array>
	<key>CFBundleInfoDictionaryVersion</key>
	<string>6.0</string>
	<key>DTPlatformVersion</key>
	<string>7.1</string>
	<key>CFBundleIconFile</key>
	<string>appicon.png</string>
	<key>DTSDKName</key>
	<string>iphoneos7.1</string>
	<key>CFBundleName</key>
	<string>TextCamera</string>
	<key>UIStatusBarStyle</key>
	<string>UIStatusBarStyleDefault</string>
	<key>LSRequiresIPhoneOS</key>
	<true/>
	<key>UIRequiresPersistentWiFi</key>
	<false/>
	<key>CFBundleDisplayName</key>
	<string>TextCamera</string>
	<key>DTSDKBuild</key>
	<string>11D167</string>
	<key>CFBundleShortVersionString</key>
	<string>2.5.0</string>
	<key>CFBundleSupportedPlatforms</key>
	<array>
		<string>iPhoneOS</string>
	</array>
	<key>UISupportedInterfaceOrientations</key>
	<array>
		<string>UIInterfaceOrientationPortrait</string>
		<string>UIInterfaceOrientationPortraitUpsideDown</string>
		<string>UIInterfaceOrientationLandscapeLeft</string>
		<string>UIInterfaceOrientationLandscapeRight</string>
	</array>
	<key>BuildMachineOSBuild</key>
	<string>13C64</string>
	<key>DTPlatformBuild</key>
	<string>11D167</string>
	<key>CFBundlePackageType</key>
	<string>APPL</string>
	<key>MinimumOSVersion</key>
	<string>5.0</string>
	<key>CFBundleDevelopmentRegion</key>
	<string>English</string>
	<key>UIPrerenderedIcon</key>
	<true/>
	<key>CFBundleVersion</key>
	<string>2.5.0</string>
	<key>DTXcodeBuild</key>
	<string>5B130a</string>
	<key>UIStatusBarHidden</key>
	<true/>
	<key>UIAppFonts</key>
	<array>
		<string>/fonts/BebasNeue.otf</string>
		<string>/fonts/Blackout-2am.ttf</string>
		<string>/fonts/ComicNoteSmooth.ttf</string>
		<string>/fonts/DESYREL_.ttf</string>
		<string>/fonts/Dion.otf</string>
		<string>/fonts/DroidSerif-BoldItalic.ttf</string>
		<string>/fonts/Edson_Comics_Bold.ttf</string>
		<string>/fonts/GeosansLight.ttf</string>
		<string>/fonts/GreatVibes-Regular.ttf</string>
		<string>/fonts/KiloGram_KG.otf</string>
		<string>/fonts/LondrinaSolid-Regular.ttf</string>
		<string>/fonts/Making-Lettering-Tall_demo.ttf</string>
		<string>/fonts/Mywriting.ttf</string>
		<string>/fonts/Nina-Bold_OTF.otf</string>
		<string>/fonts/Scratch_.ttf</string>
		<string>/fonts/SeattleAvenue.otf</string>
		<string>/fonts/SharkSoftBites.ttf</string>
		<string>/fonts/SofthandScript.ttf</string>
		<string>/fonts/Timoteo.ttf</string>
		<string>/fonts/YARDSALE.TTF</string>
		<string>/fonts/coolvetica-rg.ttf</string>
		<string>/fonts/daniel.ttf</string>
		<string>/fonts/futuramc.ttf</string>
		<string>/fonts/j.d.ttf</string>
		<string>/fonts/kimberley-bl.ttf</string>
		<string>/fonts/pincoyablack.otf</string>
		<string>/fonts/shark-party.ttf</string>
		<string>/fonts/southpaw.otf</string>
		<string>/fonts/walibi-holland.ttf</string>
	</array>
	<key>UIDeviceFamily</key>
	<array>
		<integer>1</integer>
	</array>
	<key>CFBundleIdentifier</key>
	<string>com.stendapps.textcamera</string>
	<key>CFBundleIconFiles</key>
	<array>
		<string>appicon.png</string>
		<string>appicon@2x.png</string>
		<string>appicon-72.png</string>
		<string>appicon-60.png</string>
		<string>appicon-60@2x.png</string>
		<string>appicon-76.png</string>
		<string>appicon-76@2x.png</string>
		<string>appicon-Small-50.png</string>
		<string>appicon-72@2x.png</string>
		<string>appicon-Small-50@2x.png</string>
		<string>appicon-Small.png</string>
		<string>appicon-Small@2x.png</string>
	</array>
	<key>DTXcode</key>
	<string>0510</string>
	<key>CFBundleExecutable</key>
	<string>TextCamera</string>
	<key>CFBundleSignature</key>
	<string>????</string>
	<key>DTPlatformName</key>
	<string>iphoneos</string>
	<key>CFBundleResourceSpecification</key>
	<string>ResourceRules.plist</string>
	<key>DTCompiler</key>
	<string>com.apple.compilers.llvm.clang.1_0</string>
</dict>
</plist>
