<?xml version="1.0" encoding="UTF-8"?>
<!DOCTYPE plist PUBLIC "-//Apple//DTD PLIST 1.0//EN" "http://www.apple.com/DTDs/PropertyList-1.0.dtd">
<plist version="1.0">
<dict>
	<key>DTSDKName</key>
	<string>iphoneos8.1</string>
	<key>CFBundleName</key>
	<string>mfyp</string>
	<key>DTXcode</key>
	<string>0610</string>
	<key>DTSDKBuild</key>
	<string>12B411</string>
	<key>CFBundleDevelopmentRegion</key>
	<string>en</string>
	<key>CFBundleVersion</key>
	<string>2.8.0</string>
	<key>BuildMachineOSBuild</key>
	<string>14B25</string>
	<key>DTPlatformName</key>
	<string>iphoneos</string>
	<key>CFBundleShortVersionString</key>
	<string>2.8.0</string>
	<key>CFBundlePackageType</key>
	<string>APPL</string>
	<key>CFBundleSupportedPlatforms</key>
	<array>
		<string>iPhoneOS</string>
	</array>
	<key>CFBundleInfoDictionaryVersion</key>
	<string>6.0</string>
	<key>UIRequiredDeviceCapabilities</key>
	<array>
		<string>armv7</string>
	</array>
	<key>CFBundleExecutable</key>
	<string>AGCallerCheck</string>
	<key>DTCompiler</key>
	<string>com.apple.compilers.llvm.clang.1_0</string>
	<key>UIViewControllerBasedStatusBarAppearance</key>
	<true/>
	<key>CFBundleIdentifier</key>
	<string>com.magicpocket.mobilelocation</string>
	<key>CFBundleURLTypes</key>
	<array>
		<dict>
			<key>CFBundleTypeRole</key>
			<string>Editor</string>
			<key>CFBundleURLName</key>
			<string>weixin</string>
			<key>CFBundleURLSchemes</key>
			<array>
				<string>wx076731e1e74806a7</string>
			</array>
		</dict>
		<dict>
			<key>CFBundleTypeRole</key>
			<string>Editor</string>
			<key>CFBundleURLName</key>
			<string>weibo</string>
			<key>CFBundleURLSchemes</key>
			<array>
				<string>wb2339039598</string>
			</array>
		</dict>
	</array>
	<key>DTXcodeBuild</key>
	<string>6A1052d</string>
	<key>DTPlatformVersion</key>
	<string>8.1</string>
	<key>CFBundleIcons</key>
	<dict>
		<key>CFBundlePrimaryIcon</key>
		<dict>
			<key>CFBundleIconFiles</key>
			<array>
				<string>Icon-120</string>
				<string>Icon</string>
			</array>
		</dict>
	</dict>
	<key>LSRequiresIPhoneOS</key>
	<true/>
	<key>UISupportedInterfaceOrientations</key>
	<array>
		<string>UIInterfaceOrientationPortrait</string>
	</array>
	<key>CFBundleDisplayName</key>
	<string>手机归属地</string>
	<key>CFBundleSignature</key>
	<string>????</string>
	<key>MinimumOSVersion</key>
	<string>5.1.1</string>
	<key>DTPlatformBuild</key>
	<string>12B411</string>
	<key>UIDeviceFamily</key>
	<array>
		<integer>1</integer>
	</array>
</dict>
</plist>
