<?xml version="1.0" encoding="UTF-8"?>
<!DOCTYPE plist PUBLIC "-//Apple//DTD PLIST 1.0//EN" "http://www.apple.com/DTDs/PropertyList-1.0.dtd">
<plist version="1.0">
<dict>
	<key>UIRequiredDeviceCapabilities</key>
	<array>
		<string>armv7</string>
	</array>
	<key>CFBundleURLTypes</key>
	<array>
		<dict>
			<key>CFBundleTypeRole</key>
			<string>Editor</string>
			<key>CFBundleURLSchemes</key>
			<array>
				<string>pomelo.todaywidget</string>
			</array>
			<key>CFBundleURLTypes</key>
			<array>
				<dict>
					<key>camerawidget</key>
					<string>camerawidget</string>
				</dict>
				<dict>
					<key>beautywidget</key>
					<string>beautywidget</string>
				</dict>
			</array>
			<key>CFBundleURLName</key>
			<string>todaywidget</string>
		</dict>
		<dict>
			<key>CFBundleTypeRole</key>
			<string>Editor</string>
			<key>CFBundleURLName</key>
			<string>com.meitu</string>
			<key>CFBundleURLSchemes</key>
			<array>
				<string>wb2734189087</string>
			</array>
		</dict>
		<dict>
			<key>CFBundleTypeRole</key>
			<string>Editor</string>
			<key>CFBundleURLName</key>
			<string>weixinEnglish</string>
			<key>CFBundleURLSchemes</key>
			<array>
				<string>wxab7b6ea0121bfd73</string>
			</array>
		</dict>
		<dict>
			<key>CFBundleTypeRole</key>
			<string>Editor</string>
			<key>CFBundleURLName</key>
			<string>pomelo</string>
			<key>CFBundleURLSchemes</key>
			<array>
				<string>pomelo</string>
			</array>
		</dict>
		<dict>
			<key>CFBundleTypeRole</key>
			<string>Editor</string>
			<key>CFBundleURLName</key>
			<string>weixinSimpleChinese</string>
			<key>CFBundleURLSchemes</key>
			<array>
				<string>wx4b1e35c4a2d16645</string>
			</array>
		</dict>
		<dict>
			<key>CFBundleTypeRole</key>
			<string>Editor</string>
			<key>CFBundleURLName</key>
			<string>weixinTraditionalChinese</string>
			<key>CFBundleURLSchemes</key>
			<array>
				<string>wxe730a1287701b01c</string>
			</array>
		</dict>
		<dict>
			<key>CFBundleTypeRole</key>
			<string>Editor</string>
			<key>CFBundleURLName</key>
			<string>facebook</string>
			<key>CFBundleURLSchemes</key>
			<array>
				<string>fb749515228439183</string>
			</array>
		</dict>
	</array>
	<key>CFBundleInfoDictionaryVersion</key>
	<string>6.0</string>
	<key>DTPlatformVersion</key>
	<string>8.2</string>
	<key>CFBundleName</key>
	<string>Pomelo</string>
	<key>DTSDKName</key>
	<string>iphoneos8.2</string>
	<key>UIViewControllerBasedStatusBarAppearance</key>
	<false/>
	<key>CFBundleIcons</key>
	<dict>
		<key>CFBundlePrimaryIcon</key>
		<dict>
			<key>CFBundleIconFiles</key>
			<array>
				<string>AppIcon29x29</string>
				<string>AppIcon40x40</string>
				<string>AppIcon57x57</string>
				<string>AppIcon60x60</string>
			</array>
		</dict>
	</dict>
	<key>LSRequiresIPhoneOS</key>
	<true/>
	<key>CFBundleDisplayName</key>
	<string>Pomelo</string>
	<key>DTSDKBuild</key>
	<string>12D508</string>
	<key>CFBundleShortVersionString</key>
	<string>1.5.1</string>
	<key>UISupportedInterfaceOrientations</key>
	<array>
		<string>UIInterfaceOrientationPortrait</string>
	</array>
	<key>CFBundleSupportedPlatforms</key>
	<array>
		<string>iPhoneOS</string>
	</array>
	<key>BuildMachineOSBuild</key>
	<string>14C1510</string>
	<key>DTPlatformBuild</key>
	<string>12D508</string>
	<key>CFBundlePackageType</key>
	<string>APPL</string>
	<key>DTXcodeBuild</key>
	<string>6C131e</string>
	<key>CFBundleDevelopmentRegion</key>
	<string>en</string>
	<key>UIAppFonts</key>
	<array>
		<string>Helvetica LT 47 Light Condensed.ttf</string>
		<string>HelveticaNeue LT 37 ThinCn.ttf</string>
		<string>HelveticaNeue LT 57 Cn.ttf</string>
	</array>
	<key>CFBundleVersion</key>
	<string>1.5.1</string>
	<key>UIPrerenderedIcon</key>
	<true/>
	<key>UIStatusBarHidden</key>
	<true/>
	<key>UILaunchImageFile</key>
	<string>LaunchImage</string>
	<key>FacebookAppID</key>
	<string>749515228439183</string>
	<key>UILaunchImages</key>
	<array>
		<dict>
			<key>UILaunchImageOrientation</key>
			<string>Portrait</string>
			<key>UILaunchImageName</key>
			<string>LaunchImage-700</string>
			<key>UILaunchImageSize</key>
			<string>{320, 480}</string>
			<key>UILaunchImageMinimumOSVersion</key>
			<string>7.0</string>
		</dict>
		<dict>
			<key>UILaunchImageOrientation</key>
			<string>Portrait</string>
			<key>UILaunchImageName</key>
			<string>LaunchImage-700-568h</string>
			<key>UILaunchImageSize</key>
			<string>{320, 568}</string>
			<key>UILaunchImageMinimumOSVersion</key>
			<string>7.0</string>
		</dict>
	</array>
	<key>MinimumOSVersion</key>
	<string>7.0</string>
	<key>UILaunchStoryboardName</key>
	<string>Launch Screen</string>
	<key>UIDeviceFamily</key>
	<array>
		<integer>1</integer>
	</array>
	<key>CFBundleIdentifier</key>
	<string>com.meitu.pomelo</string>
	<key>DTXcode</key>
	<string>0620</string>
	<key>CFBundleExecutable</key>
	<string>Pomelo</string>
	<key>CFBundleIcons~ipad</key>
	<dict>
		<key>CFBundlePrimaryIcon</key>
		<dict>
			<key>CFBundleIconFiles</key>
			<array>
				<string>AppIcon29x29</string>
				<string>AppIcon40x40</string>
				<string>AppIcon57x57</string>
				<string>AppIcon60x60</string>
				<string>AppIcon50x50</string>
				<string>AppIcon72x72</string>
				<string>AppIcon76x76</string>
			</array>
		</dict>
	</dict>
	<key>CFBundleSignature</key>
	<string>????</string>
	<key>DTPlatformName</key>
	<string>iphoneos</string>
	<key>DTCompiler</key>
	<string>com.apple.compilers.llvm.clang.1_0</string>
</dict>
</plist>
